[
    {
        "ID": "155989",
        "DATE_CREATE": "2022-05-16T07:17:56+03:00",
        "STAGE_ID": "5",
        "UF_CRM_5903C16BDF7A7": "243579615",
        "UF_CRM_595ED493B6E5C": "3003"
    },
    {
        "ID": "155991",
        "DATE_CREATE": "2022-05-16T08:01:10+03:00",
        "STAGE_ID": "5",
        "UF_CRM_5903C16BDF7A7": "243579921",
        "UF_CRM_595ED493B6E5C": "3003"
    },
    {
        "ID": "155999",
        "DATE_CREATE": "2022-05-16T08:33:00+03:00",
        "STAGE_ID": "5",
        "UF_CRM_5903C16BDF7A7": "243580243",
        "UF_CRM_595ED493B6E5C": "3003"
    },
    {
        "ID": "156002",
        "DATE_CREATE": "2022-05-16T08:44:47+03:00",
        "STAGE_ID": "5",
        "UF_CRM_5903C16BDF7A7": "243580456 / 243580457",
        "UF_CRM_595ED493B6E5C": "3058"
    },
    {
        "ID": "156006",
        "DATE_CREATE": "2022-05-16T08:56:44+03:00",
        "STAGE_ID": "5",
        "UF_CRM_5903C16BDF7A7": "243580687",
        "UF_CRM_595ED493B6E5C": "3003"
    },
    {
        "ID": "156009",
        "DATE_CREATE": "2022-05-16T09:04:53+03:00",
        "STAGE_ID": "5",
        "UF_CRM_5903C16BDF7A7": "243580792",
        "UF_CRM_595ED493B6E5C": "3058"
    },
    {
        "ID": "156012",
        "DATE_CREATE": "2022-05-16T09:31:57+03:00",
        "STAGE_ID": "5",
        "UF_CRM_5903C16BDF7A7": "243581270",
        "UF_CRM_595ED493B6E5C": "3003"
    },
    {
        "ID": "156022",
        "DATE_CREATE": "2022-05-16T09:53:02+03:00",
        "STAGE_ID": "5",
        "UF_CRM_5903C16BDF7A7": "243582293",
        "UF_CRM_595ED493B6E5C": "3058"
    },
    {
        "ID": "156023",
        "DATE_CREATE": "2022-05-16T10:06:18+03:00",
        "STAGE_ID": "5",
        "UF_CRM_5903C16BDF7A7": "243582542",
        "UF_CRM_595ED493B6E5C": "3002"
    },
    {
        "ID": "156026",
        "DATE_CREATE": "2022-05-16T10:19:33+03:00",
        "STAGE_ID": "5",
        "UF_CRM_5903C16BDF7A7": "243583577",
        "UF_CRM_595ED493B6E5C": "3003"
    },
    {
        "ID": "156033",
        "DATE_CREATE": "2022-05-16T10:51:51+03:00",
        "STAGE_ID": "5",
        "UF_CRM_5903C16BDF7A7": "243584661 243584660",
        "UF_CRM_595ED493B6E5C": "3003"
    },
    {
        "ID": "156035",
        "DATE_CREATE": "2022-05-16T10:57:42+03:00",
        "STAGE_ID": "5",
        "UF_CRM_5903C16BDF7A7": "243585312",
        "UF_CRM_595ED493B6E5C": "3058"
    },
    {
        "ID": "156036",
        "DATE_CREATE": "2022-05-16T10:58:02+03:00",
        "STAGE_ID": "5",
        "UF_CRM_5903C16BDF7A7": "243585270",
        "UF_CRM_595ED493B6E5C": "3058"
    },
    {
        "ID": "156038",
        "DATE_CREATE": "2022-05-16T11:03:28+03:00",
        "STAGE_ID": "5",
        "UF_CRM_5903C16BDF7A7": "243584923 / 243584924",
        "UF_CRM_595ED493B6E5C": "3003"
    },
    {
        "ID": "156046",
        "DATE_CREATE": "2022-05-16T11:26:06+03:00",
        "STAGE_ID": "5",
        "UF_CRM_5903C16BDF7A7": "243586632",
        "UF_CRM_595ED493B6E5C": "3058"
    },
    {
        "ID": "156055",
        "DATE_CREATE": "2022-05-16T12:10:02+03:00",
        "STAGE_ID": "5",
        "UF_CRM_5903C16BDF7A7": "243588724",
        "UF_CRM_595ED493B6E5C": "3003"
    },
    {
        "ID": "156057",
        "DATE_CREATE": "2022-05-16T12:16:08+03:00",
        "STAGE_ID": "5",
        "UF_CRM_5903C16BDF7A7": "243589010 243589011",
        "UF_CRM_595ED493B6E5C": "3058"
    },
    {
        "ID": "156062",
        "DATE_CREATE": "2022-05-16T12:26:55+03:00",
        "STAGE_ID": "5",
        "UF_CRM_5903C16BDF7A7": "243589434",
        "UF_CRM_595ED493B6E5C": "3003"
    },
    {
        "ID": "156063",
        "DATE_CREATE": "2022-05-16T12:29:14+03:00",
        "STAGE_ID": "5",
        "UF_CRM_5903C16BDF7A7": "243589782 243589783",
        "UF_CRM_595ED493B6E5C": "3003"
    },
    {
        "ID": "156064",
        "DATE_CREATE": "2022-05-16T12:38:36+03:00",
        "STAGE_ID": "5",
        "UF_CRM_5903C16BDF7A7": "243590194 243590195",
        "UF_CRM_595ED493B6E5C": "3003"
    },
    {
        "ID": "156066",
        "DATE_CREATE": "2022-05-16T12:41:17+03:00",
        "STAGE_ID": "5",
        "UF_CRM_5903C16BDF7A7": "243589383 / 243589384",
        "UF_CRM_595ED493B6E5C": "3058"
    },
    {
        "ID": "156067",
        "DATE_CREATE": "2022-05-16T12:45:43+03:00",
        "STAGE_ID": "5",
        "UF_CRM_5903C16BDF7A7": "243590238",
        "UF_CRM_595ED493B6E5C": "3003"
    },
    {
        "ID": "156074",
        "DATE_CREATE": "2022-05-16T13:06:41+03:00",
        "STAGE_ID": "5",
        "UF_CRM_5903C16BDF7A7": "243591220",
        "UF_CRM_595ED493B6E5C": "3003"
    },
    {
        "ID": "156075",
        "DATE_CREATE": "2022-05-16T13:08:23+03:00",
        "STAGE_ID": "5",
        "UF_CRM_5903C16BDF7A7": "243591050",
        "UF_CRM_595ED493B6E5C": "3002"
    },
    {
        "ID": "156078",
        "DATE_CREATE": "2022-05-16T13:19:18+03:00",
        "STAGE_ID": "5",
        "UF_CRM_5903C16BDF7A7": "243591933",
        "UF_CRM_595ED493B6E5C": "3003"
    },
    {
        "ID": "156080",
        "DATE_CREATE": "2022-05-16T13:36:06+03:00",
        "STAGE_ID": "5",
        "UF_CRM_5903C16BDF7A7": "243593092",
        "UF_CRM_595ED493B6E5C": "3058"
    },
    {
        "ID": "156081",
        "DATE_CREATE": "2022-05-16T13:42:02+03:00",
        "STAGE_ID": "5",
        "UF_CRM_5903C16BDF7A7": "243593184 / 243593185",
        "UF_CRM_595ED493B6E5C": "3058"
    },
    {
        "ID": "156085",
        "DATE_CREATE": "2022-05-16T13:53:16+03:00",
        "STAGE_ID": "5",
        "UF_CRM_5903C16BDF7A7": "243593859 / 243593860",
        "UF_CRM_595ED493B6E5C": "3002"
    },
    {
        "ID": "156086",
        "DATE_CREATE": "2022-05-16T13:53:22+03:00",
        "STAGE_ID": "5",
        "UF_CRM_5903C16BDF7A7": "243593547",
        "UF_CRM_595ED493B6E5C": "3002"
    },
    {
        "ID": "156089",
        "DATE_CREATE": "2022-05-16T14:05:40+03:00",
        "STAGE_ID": "5",
        "UF_CRM_5903C16BDF7A7": "243594519 / 243594520",
        "UF_CRM_595ED493B6E5C": "3058"
    },
    {
        "ID": "156095",
        "DATE_CREATE": "2022-05-16T14:16:51+03:00",
        "STAGE_ID": "5",
        "UF_CRM_5903C16BDF7A7": "243595071",
        "UF_CRM_595ED493B6E5C": "3058"
    },
    {
        "ID": "156096",
        "DATE_CREATE": "2022-05-16T14:17:28+03:00",
        "STAGE_ID": "5",
        "UF_CRM_5903C16BDF7A7": "243593899",
        "UF_CRM_595ED493B6E5C": "3003"
    },
    {
        "ID": "156098",
        "DATE_CREATE": "2022-05-16T14:25:02+03:00",
        "STAGE_ID": "5",
        "UF_CRM_5903C16BDF7A7": "243595584",
        "UF_CRM_595ED493B6E5C": "3003"
    },
    {
        "ID": "156100",
        "DATE_CREATE": "2022-05-16T14:26:08+03:00",
        "STAGE_ID": "5",
        "UF_CRM_5903C16BDF7A7": "243595362",
        "UF_CRM_595ED493B6E5C": "3058"
    },
    {
        "ID": "156101",
        "DATE_CREATE": "2022-05-16T14:32:41+03:00",
        "STAGE_ID": "5",
        "UF_CRM_5903C16BDF7A7": "243595997",
        "UF_CRM_595ED493B6E5C": "3002"
    },
    {
        "ID": "156113",
        "DATE_CREATE": "2022-05-16T15:34:21+03:00",
        "STAGE_ID": "5",
        "UF_CRM_5903C16BDF7A7": "243598835 ",
        "UF_CRM_595ED493B6E5C": "3002"
    },
    {
        "ID": "156117",
        "DATE_CREATE": "2022-05-16T15:49:33+03:00",
        "STAGE_ID": "5",
        "UF_CRM_5903C16BDF7A7": "243599373 ",
        "UF_CRM_595ED493B6E5C": "3002"
    },
    {
        "ID": "156120",
        "DATE_CREATE": "2022-05-16T15:54:06+03:00",
        "STAGE_ID": "5",
        "UF_CRM_5903C16BDF7A7": "243599438",
        "UF_CRM_595ED493B6E5C": "3003"
    },
    {
        "ID": "156122",
        "DATE_CREATE": "2022-05-16T15:56:21+03:00",
        "STAGE_ID": "5",
        "UF_CRM_5903C16BDF7A7": "243598927",
        "UF_CRM_595ED493B6E5C": "3003"
    },
    {
        "ID": "156124",
        "DATE_CREATE": "2022-05-16T16:03:51+03:00",
        "STAGE_ID": "5",
        "UF_CRM_5903C16BDF7A7": "243599799",
        "UF_CRM_595ED493B6E5C": "3058"
    },
    {
        "ID": "156134",
        "DATE_CREATE": "2022-05-16T17:37:35+03:00",
        "STAGE_ID": "5",
        "UF_CRM_5903C16BDF7A7": "243602631",
        "UF_CRM_595ED493B6E5C": "3002"
    },
    {
        "ID": "156137",
        "DATE_CREATE": "2022-05-16T17:57:58+03:00",
        "STAGE_ID": "5",
        "UF_CRM_5903C16BDF7A7": "243601564 243603310",
        "UF_CRM_595ED493B6E5C": "3002"
    },
    {
        "ID": "156140",
        "DATE_CREATE": "2022-05-16T18:03:06+03:00",
        "STAGE_ID": "5",
        "UF_CRM_5903C16BDF7A7": "243602571",
        "UF_CRM_595ED493B6E5C": "3058"
    },
    {
        "ID": "156142",
        "DATE_CREATE": "2022-05-16T18:12:34+03:00",
        "STAGE_ID": "5",
        "UF_CRM_5903C16BDF7A7": "243603639",
        "UF_CRM_595ED493B6E5C": "3003"
    },
    {
        "ID": "156152",
        "DATE_CREATE": "2022-05-16T19:13:26+03:00",
        "STAGE_ID": "5",
        "UF_CRM_5903C16BDF7A7": "243604812",
        "UF_CRM_595ED493B6E5C": "3002"
    },
    {
        "ID": "156160",
        "DATE_CREATE": "2022-05-16T19:43:45+03:00",
        "STAGE_ID": "5",
        "UF_CRM_5903C16BDF7A7": "243604867",
        "UF_CRM_595ED493B6E5C": "3003"
    },
    {
        "ID": "156163",
        "DATE_CREATE": "2022-05-16T19:53:55+03:00",
        "STAGE_ID": "5",
        "UF_CRM_5903C16BDF7A7": "243606484 / 243606485",
        "UF_CRM_595ED493B6E5C": "3003"
    },
    {
        "ID": "156164",
        "DATE_CREATE": "2022-05-16T19:57:33+03:00",
        "STAGE_ID": "5",
        "UF_CRM_5903C16BDF7A7": "243488746",
        "UF_CRM_595ED493B6E5C": "3002"
    },
    {
        "ID": "156167",
        "DATE_CREATE": "2022-05-16T20:14:08+03:00",
        "STAGE_ID": "5",
        "UF_CRM_5903C16BDF7A7": "243607020 / 243607021",
        "UF_CRM_595ED493B6E5C": "3058"
    },
    {
        "ID": "156173",
        "DATE_CREATE": "2022-05-16T20:55:40+03:00",
        "STAGE_ID": "5",
        "UF_CRM_5903C16BDF7A7": "243608042",
        "UF_CRM_595ED493B6E5C": "3058"
    },
    {
        "ID": "156178",
        "DATE_CREATE": "2022-05-16T21:55:37+03:00",
        "STAGE_ID": "5",
        "UF_CRM_5903C16BDF7A7": "243589762 243589763",
        "UF_CRM_595ED493B6E5C": "3058"
    }
]